stlcgpp/formula.py
stlcgpp/tests.py
stlcgpp/utils.py
stlcgpp/viz.py
stlcgpp-0.0.2.dist-info/METADATA
stlcgpp-0.0.2.dist-info/WHEEL
stlcgpp-0.0.2.dist-info/top_level.txt
stlcgpp-0.0.2.dist-info/RECORD
